LICENSE
README.md
setup.py
bivalve/__init__.py
bivalve/agent.py
bivalve/aio.py
bivalve/call.py
bivalve/cli.py
bivalve/datatypes.py
bivalve/nio.py
bivalve/util.py
bivalve.egg-info/PKG-INFO
bivalve.egg-info/SOURCES.txt
bivalve.egg-info/dependency_links.txt
bivalve.egg-info/entry_points.txt
bivalve.egg-info/requires.txt
bivalve.egg-info/top_level.txt
bivalve/example/__init__.py
bivalve/example/bridge.py
bivalve/example/client.py
bivalve/example/path_client.py
bivalve/example/path_server.py
bivalve/example/server.py