Metadata-Version: 2.1
Name: bivalve
Version: 2.3.0
Summary: A bi-directional shell-like socket protocol framework using asyncio.
Home-page: https://github.com/lainproliant/bivalve
Author: Lain Musgrove (lainproliant)
Author-email: lainproliant@gmail.com
License: BSD
Keywords: network sockets protocol shell
Classifier: Development Status :: 5 - Production/Stable
Classifier: Intended Audience :: Developers
Classifier: Topic :: Software Development :: Libraries :: Application Frameworks
Classifier: License :: OSI Approved :: BSD License
Classifier: Programming Language :: Python :: 3.10
License-File: LICENSE
Requires-Dist: commandmap==1.0.0
Requires-Dist: waterlog==1.0.0
